pyramid_saml/__init__.py
pyramid_saml-0.0.2.dist-info/LICENSE
pyramid_saml-0.0.2.dist-info/METADATA
pyramid_saml-0.0.2.dist-info/WHEEL
pyramid_saml-0.0.2.dist-info/top_level.txt
pyramid_saml-0.0.2.dist-info/RECORD
