Metadata-Version: 2.1
Name: pyramid-saml
Version: 0.0.2
Summary: Pyramid SAML
Home-page: https://gitlab.com/geo-bl-ch/pyramid_saml
Author: Karsten Deininger
Author-email: karsten.deininger@bl.ch
License: UNKNOWN
Keywords: web pyramid saml
Platform: UNKNOWN
Classifier: License :: OSI Approved :: BSD License
Classifier: Development Status :: 5 - Production/Stable
Classifier: Programming Language :: Python :: 3.7
Classifier: Programming Language :: Python :: 3.8
Classifier: Programming Language :: Python :: 3.9
Classifier: Programming Language :: Python :: 3.10
Classifier: Framework :: Pyramid
Classifier: Topic :: Internet :: WWW/HTTP
License-File: LICENSE
Requires-Dist: pyramid
Requires-Dist: python3-saml
